modex_client/__init__.py
modex_client/utils.py
modex_client/api/__init__.py
modex_client/api/oauth.py
modex_client/api/request.py
modex_client/api/user_management.py
modex_client-0.1.dist-info/LICENSE
modex_client-0.1.dist-info/METADATA
modex_client-0.1.dist-info/WHEEL
modex_client-0.1.dist-info/top_level.txt
modex_client-0.1.dist-info/RECORD
